python2d/__init__.py
python2d/storage.py
python2d-0.0.1.dist-info/METADATA
python2d-0.0.1.dist-info/WHEEL
python2d-0.0.1.dist-info/top_level.txt
python2d-0.0.1.dist-info/RECORD
