Metadata-Version: 2.1
Name: python2d
Version: 0.0.1
Summary: Python library to easily create 2d games
Home-page: http://github.com/greencarrot5/python-2d-game-library
Author: greencarrot5
Author-email: seppevanammel@gmail.com
License: MIT
Platform: UNKNOWN
Classifier: Programming Language :: Python :: 3
Classifier: License :: OSI Approved :: MIT License
Classifier: Operating System :: OS Independent
Requires-Dist: pillow
